themooch.py
themooch-0.1.dist-info/LICENSE
themooch-0.1.dist-info/WHEEL
themooch-0.1.dist-info/METADATA
themooch-0.1.dist-info/RECORD
