Metadata-Version: 2.1
Name: themooch
Version: 0.1
Summary: Takes in two datetime objects, returns the length of time in scaramuccis
Home-page: https://github.com/snachman/themooch
License: UNKNOWN
Author: Sam Nachman
Author-email: shnachman@gmail.com
